[
    {
        "orderId": 1,
        "bookingId": 7,
        "serviceId": 3,
        "createdAt": "2022-04-15T12:38:18",
        "status": 2,
        "note": ""
    },
    {
        "orderId": 2,
        "bookingId": 17,
        "serviceId": 1,
        "createdAt": "2022-04-15T11:36:19",
        "status": 2,
        "note": ""
    },
    {
        "orderId": 3,
        "bookingId": 19,
        "serviceId": 2,
        "createdAt": "2022-04-15T12:39:55",
        "status": 2,
        "note": ""
    },
    {
        "orderId": 4,
        "bookingId": 22,
        "serviceId": 3,
        "createdAt": "2022-04-15T12:58:25",
        "status": 2,
        "note": ""
    },
    {
        "orderId": 5,
        "bookingId": 24,
        "serviceId": 1,
        "createdAt": "2022-04-15T11:46:31",
        "status": 2,
        "note": ""
    },
    {
        "orderId": 6,
        "bookingId": 25,
        "serviceId": 4,
        "createdAt": "2022-04-15T10:44:46",
        "status": 2,
        "note": ""
    },
    {
        "orderId": 7,
        "bookingId": 30,
        "serviceId": 2,
        "createdAt": "2022-04-15T12:48:13",
        "status": 2,
        "note": ""
    },
    {
        "orderId": 8,
        "bookingId": 32,
        "serviceId": 5,
        "createdAt": "2022-04-15T11:57:47",
        "status": 2,
        "note": ""
    },
    {
        "orderId": 9,
        "bookingId": 39,
        "serviceId": 1,
        "createdAt": "2022-04-15T11:41:31",
        "status": 2,
        "note": ""
    },
    {
        "orderId": 10,
        "bookingId": 45,
        "serviceId": 2,
        "createdAt": "2022-04-15T11:28:54",
        "status": 2,
        "note": ""
    },
    {
        "orderId": 11,
        "bookingId": 6,
        "serviceId": 5,
        "createdAt": "2022-04-16T12:51:30",
        "status": 2,
        "note": ""
    },
    {
        "orderId": 12,
        "bookingId": 10,
        "serviceId": 5,
        "createdAt": "2022-04-16T12:58:53",
        "status": 2,
        "note": ""
    },
    {
        "orderId": 13,
        "bookingId": 21,
        "serviceId": 5,
        "createdAt": "2022-04-16T11:39:51",
        "status": 2,
        "note": ""
    },
    {
        "orderId": 14,
        "bookingId": 28,
        "serviceId": 4,
        "createdAt": "2022-04-16T11:38:26",
        "status": 2,
        "note": ""
    },
    {
        "orderId": 15,
        "bookingId": 32,
        "serviceId": 3,
        "createdAt": "2022-04-16T10:14:37",
        "status": 2,
        "note": ""
    },
    {
        "orderId": 16,
        "bookingId": 40,
        "serviceId": 2,
        "createdAt": "2022-04-16T12:10:25",
        "status": 2,
        "note": ""
    },
    {
        "orderId": 17,
        "bookingId": 42,
        "serviceId": 2,
        "createdAt": "2022-04-16T10:21:51",
        "status": 2,
        "note": ""
    },
    {
        "orderId": 18,
        "bookingId": 46,
        "serviceId": 1,
        "createdAt": "2022-04-16T12:42:49",
        "status": 2,
        "note": ""
    },
    {
        "orderId": 19,
        "bookingId": 48,
        "serviceId": 4,
        "createdAt": "2022-04-16T12:19:46",
        "status": 2,
        "note": ""
    },
    {
        "orderId": 20,
        "bookingId": 49,
        "serviceId": 5,
        "createdAt": "2022-04-16T11:40:36",
        "status": 2,
        "note": ""
    },
    {
        "orderId": 21,
        "bookingId": 25,
        "serviceId": 3,
        "createdAt": "2022-04-17T10:14:36",
        "status": 2,
        "note": ""
    },
    {
        "orderId": 22,
        "bookingId": 34,
        "serviceId": 1,
        "createdAt": "2022-04-17T10:34:33",
        "status": 2,
        "note": ""
    },
    {
        "orderId": 23,
        "bookingId": 38,
        "serviceId": 2,
        "createdAt": "2022-04-17T12:12:33",
        "status": 2,
        "note": ""
    },
    {
        "orderId": 24,
        "bookingId": 53,
        "serviceId": 4,
        "createdAt": "2022-04-17T12:53:10",
        "status": 2,
        "note": ""
    },
    {
        "orderId": 25,
        "bookingId": 55,
        "serviceId": 2,
        "createdAt": "2022-04-17T11:16:30",
        "status": 2,
        "note": ""
    },
    {
        "orderId": 26,
        "bookingId": 58,
        "serviceId": 2,
        "createdAt": "2022-04-17T12:43:58",
        "status": 2,
        "note": ""
    },
    {
        "orderId": 27,
        "bookingId": 59,
        "serviceId": 4,
        "createdAt": "2022-04-17T11:46:16",
        "status": 2,
        "note": ""
    },
    {
        "orderId": 28,
        "bookingId": 2,
        "serviceId": 3,
        "createdAt": "2022-04-18T10:56:50",
        "status": 2,
        "note": ""
    },
    {
        "orderId": 29,
        "bookingId": 42,
        "serviceId": 3,
        "createdAt": "2022-04-18T10:55:49",
        "status": 2,
        "note": ""
    },
    {
        "orderId": 30,
        "bookingId": 50,
        "serviceId": 2,
        "createdAt": "2022-04-18T12:49:47",
        "status": 2,
        "note": ""
    },
    {
        "orderId": 31,
        "bookingId": 58,
        "serviceId": 2,
        "createdAt": "2022-04-18T11:12:17",
        "status": 2,
        "note": ""
    },
    {
        "orderId": 32,
        "bookingId": 64,
        "serviceId": 4,
        "createdAt": "2022-04-18T11:18:16",
        "status": 2,
        "note": ""
    },
    {
        "orderId": 33,
        "bookingId": 66,
        "serviceId": 5,
        "createdAt": "2022-04-18T12:42:32",
        "status": 2,
        "note": ""
    },
    {
        "orderId": 34,
        "bookingId": 81,
        "serviceId": 1,
        "createdAt": "2022-04-18T12:29:47",
        "status": 2,
        "note": ""
    },
    {
        "orderId": 35,
        "bookingId": 31,
        "serviceId": 4,
        "createdAt": "2022-04-19T11:15:22",
        "status": 2,
        "note": ""
    },
    {
        "orderId": 36,
        "bookingId": 42,
        "serviceId": 3,
        "createdAt": "2022-04-19T12:55:52",
        "status": 2,
        "note": ""
    },
    {
        "orderId": 37,
        "bookingId": 53,
        "serviceId": 2,
        "createdAt": "2022-04-19T12:13:43",
        "status": 2,
        "note": ""
    },
    {
        "orderId": 38,
        "bookingId": 60,
        "serviceId": 5,
        "createdAt": "2022-04-19T11:34:17",
        "status": 2,
        "note": ""
    },
    {
        "orderId": 39,
        "bookingId": 66,
        "serviceId": 4,
        "createdAt": "2022-04-19T12:50:12",
        "status": 2,
        "note": ""
    },
    {
        "orderId": 40,
        "bookingId": 69,
        "serviceId": 1,
        "createdAt": "2022-04-19T12:21:10",
        "status": 2,
        "note": ""
    },
    {
        "orderId": 41,
        "bookingId": 78,
        "serviceId": 1,
        "createdAt": "2022-04-19T11:40:18",
        "status": 2,
        "note": ""
    },
    {
        "orderId": 42,
        "bookingId": 87,
        "serviceId": 3,
        "createdAt": "2022-04-19T10:32:18",
        "status": 2,
        "note": ""
    },
    {
        "orderId": 43,
        "bookingId": 88,
        "serviceId": 3,
        "createdAt": "2022-04-19T12:33:27",
        "status": 2,
        "note": ""
    },
    {
        "orderId": 44,
        "bookingId": 89,
        "serviceId": 5,
        "createdAt": "2022-04-19T11:58:58",
        "status": 2,
        "note": ""
    },
    {
        "orderId": 45,
        "bookingId": 91,
        "serviceId": 5,
        "createdAt": "2022-04-19T12:14:19",
        "status": 2,
        "note": ""
    },
    {
        "orderId": 46,
        "bookingId": 54,
        "serviceId": 3,
        "createdAt": "2022-04-20T11:31:28",
        "status": 2,
        "note": ""
    },
    {
        "orderId": 47,
        "bookingId": 57,
        "serviceId": 3,
        "createdAt": "2022-04-20T11:25:54",
        "status": 2,
        "note": ""
    },
    {
        "orderId": 48,
        "bookingId": 69,
        "serviceId": 3,
        "createdAt": "2022-04-20T11:26:17",
        "status": 2,
        "note": ""
    },
    {
        "orderId": 49,
        "bookingId": 80,
        "serviceId": 3,
        "createdAt": "2022-04-20T10:57:16",
        "status": 2,
        "note": ""
    },
    {
        "orderId": 50,
        "bookingId": 85,
        "serviceId": 1,
        "createdAt": "2022-04-20T12:15:50",
        "status": 2,
        "note": ""
    },
    {
        "orderId": 51,
        "bookingId": 86,
        "serviceId": 2,
        "createdAt": "2022-04-20T11:12:57",
        "status": 2,
        "note": ""
    },
    {
        "orderId": 52,
        "bookingId": 89,
        "serviceId": 5,
        "createdAt": "2022-04-20T10:49:44",
        "status": 2,
        "note": ""
    },
    {
        "orderId": 53,
        "bookingId": 91,
        "serviceId": 4,
        "createdAt": "2022-04-20T11:13:21",
        "status": 2,
        "note": ""
    },
    {
        "orderId": 54,
        "bookingId": 93,
        "serviceId": 1,
        "createdAt": "2022-04-20T10:34:22",
        "status": 2,
        "note": ""
    },
    {
        "orderId": 55,
        "bookingId": 101,
        "serviceId": 4,
        "createdAt": "2022-04-20T10:23:18",
        "status": 2,
        "note": ""
    },
    {
        "orderId": 56,
        "bookingId": 50,
        "serviceId": 3,
        "createdAt": "2022-04-21T12:28:21",
        "status": 2,
        "note": ""
    },
    {
        "orderId": 57,
        "bookingId": 54,
        "serviceId": 2,
        "createdAt": "2022-04-21T10:14:39",
        "status": 2,
        "note": ""
    },
    {
        "orderId": 58,
        "bookingId": 63,
        "serviceId": 4,
        "createdAt": "2022-04-21T11:40:29",
        "status": 2,
        "note": ""
    },
    {
        "orderId": 59,
        "bookingId": 69,
        "serviceId": 3,
        "createdAt": "2022-04-21T11:38:58",
        "status": 2,
        "note": ""
    },
    {
        "orderId": 60,
        "bookingId": 80,
        "serviceId": 4,
        "createdAt": "2022-04-21T12:45:18",
        "status": 2,
        "note": ""
    },
    {
        "orderId": 61,
        "bookingId": 90,
        "serviceId": 5,
        "createdAt": "2022-04-21T11:43:39",
        "status": 2,
        "note": ""
    },
    {
        "orderId": 62,
        "bookingId": 91,
        "serviceId": 2,
        "createdAt": "2022-04-21T12:29:16",
        "status": 2,
        "note": ""
    },
    {
        "orderId": 63,
        "bookingId": 93,
        "serviceId": 4,
        "createdAt": "2022-04-21T12:48:41",
        "status": 2,
        "note": ""
    },
    {
        "orderId": 64,
        "bookingId": 96,
        "serviceId": 1,
        "createdAt": "2022-04-21T11:48:49",
        "status": 2,
        "note": ""
    },
    {
        "orderId": 65,
        "bookingId": 103,
        "serviceId": 5,
        "createdAt": "2022-04-21T12:35:48",
        "status": 2,
        "note": ""
    },
    {
        "orderId": 66,
        "bookingId": 117,
        "serviceId": 1,
        "createdAt": "2022-04-21T11:28:45",
        "status": 2,
        "note": ""
    },
    {
        "orderId": 67,
        "bookingId": 63,
        "serviceId": 1,
        "createdAt": "2022-04-22T11:45:38",
        "status": 2,
        "note": ""
    },
    {
        "orderId": 68,
        "bookingId": 88,
        "serviceId": 1,
        "createdAt": "2022-04-22T11:39:46",
        "status": 2,
        "note": ""
    },
    {
        "orderId": 69,
        "bookingId": 93,
        "serviceId": 5,
        "createdAt": "2022-04-22T12:19:10",
        "status": 2,
        "note": ""
    },
    {
        "orderId": 70,
        "bookingId": 95,
        "serviceId": 2,
        "createdAt": "2022-04-22T12:31:38",
        "status": 2,
        "note": ""
    },
    {
        "orderId": 71,
        "bookingId": 102,
        "serviceId": 5,
        "createdAt": "2022-04-22T10:38:56",
        "status": 2,
        "note": ""
    },
    {
        "orderId": 72,
        "bookingId": 110,
        "serviceId": 4,
        "createdAt": "2022-04-22T10:29:32",
        "status": 2,
        "note": ""
    },
    {
        "orderId": 73,
        "bookingId": 118,
        "serviceId": 5,
        "createdAt": "2022-04-22T11:47:13",
        "status": 2,
        "note": ""
    },
    {
        "orderId": 74,
        "bookingId": 120,
        "serviceId": 2,
        "createdAt": "2022-04-22T12:43:10",
        "status": 2,
        "note": ""
    },
    {
        "orderId": 75,
        "bookingId": 85,
        "serviceId": 5,
        "createdAt": "2022-04-23T11:19:50",
        "status": 2,
        "note": ""
    },
    {
        "orderId": 76,
        "bookingId": 93,
        "serviceId": 4,
        "createdAt": "2022-04-23T10:48:14",
        "status": 2,
        "note": ""
    },
    {
        "orderId": 77,
        "bookingId": 115,
        "serviceId": 4,
        "createdAt": "2022-04-23T12:24:21",
        "status": 2,
        "note": ""
    },
    {
        "orderId": 78,
        "bookingId": 117,
        "serviceId": 2,
        "createdAt": "2022-04-23T11:33:33",
        "status": 2,
        "note": ""
    },
    {
        "orderId": 79,
        "bookingId": 121,
        "serviceId": 4,
        "createdAt": "2022-04-23T11:41:40",
        "status": 2,
        "note": ""
    },
    {
        "orderId": 80,
        "bookingId": 122,
        "serviceId": 3,
        "createdAt": "2022-04-23T11:42:47",
        "status": 2,
        "note": ""
    },
    {
        "orderId": 81,
        "bookingId": 125,
        "serviceId": 5,
        "createdAt": "2022-04-23T10:57:49",
        "status": 2,
        "note": ""
    },
    {
        "orderId": 82,
        "bookingId": 126,
        "serviceId": 1,
        "createdAt": "2022-04-23T10:15:53",
        "status": 2,
        "note": ""
    },
    {
        "orderId": 83,
        "bookingId": 127,
        "serviceId": 1,
        "createdAt": "2022-04-23T12:46:46",
        "status": 2,
        "note": ""
    },
    {
        "orderId": 84,
        "bookingId": 130,
        "serviceId": 2,
        "createdAt": "2022-04-23T10:22:17",
        "status": 2,
        "note": ""
    },
    {
        "orderId": 85,
        "bookingId": 145,
        "serviceId": 4,
        "createdAt": "2022-04-23T11:49:30",
        "status": 2,
        "note": ""
    },
    {
        "orderId": 86,
        "bookingId": 89,
        "serviceId": 3,
        "createdAt": "2022-04-24T12:59:21",
        "status": 2,
        "note": ""
    },
    {
        "orderId": 87,
        "bookingId": 100,
        "serviceId": 5,
        "createdAt": "2022-04-24T12:46:14",
        "status": 2,
        "note": ""
    },
    {
        "orderId": 88,
        "bookingId": 111,
        "serviceId": 3,
        "createdAt": "2022-04-24T10:40:20",
        "status": 2,
        "note": ""
    },
    {
        "orderId": 89,
        "bookingId": 114,
        "serviceId": 5,
        "createdAt": "2022-04-24T10:22:48",
        "status": 2,
        "note": ""
    },
    {
        "orderId": 90,
        "bookingId": 116,
        "serviceId": 5,
        "createdAt": "2022-04-24T12:59:52",
        "status": 2,
        "note": ""
    },
    {
        "orderId": 91,
        "bookingId": 117,
        "serviceId": 1,
        "createdAt": "2022-04-24T12:55:46",
        "status": 2,
        "note": ""
    },
    {
        "orderId": 92,
        "bookingId": 128,
        "serviceId": 1,
        "createdAt": "2022-04-24T11:40:35",
        "status": 2,
        "note": ""
    },
    {
        "orderId": 93,
        "bookingId": 141,
        "serviceId": 4,
        "createdAt": "2022-04-24T11:11:52",
        "status": 2,
        "note": ""
    },
    {
        "orderId": 94,
        "bookingId": 142,
        "serviceId": 2,
        "createdAt": "2022-04-24T11:29:54",
        "status": 2,
        "note": ""
    },
    {
        "orderId": 95,
        "bookingId": 144,
        "serviceId": 3,
        "createdAt": "2022-04-24T12:50:27",
        "status": 2,
        "note": ""
    },
    {
        "orderId": 96,
        "bookingId": 147,
        "serviceId": 2,
        "createdAt": "2022-04-24T10:11:12",
        "status": 2,
        "note": ""
    },
    {
        "orderId": 97,
        "bookingId": 151,
        "serviceId": 5,
        "createdAt": "2022-04-24T11:44:19",
        "status": 2,
        "note": ""
    },
    {
        "orderId": 98,
        "bookingId": 100,
        "serviceId": 5,
        "createdAt": "2022-04-25T12:48:11",
        "status": 2,
        "note": ""
    },
    {
        "orderId": 99,
        "bookingId": 106,
        "serviceId": 1,
        "createdAt": "2022-04-25T10:54:55",
        "status": 2,
        "note": ""
    },
    {
        "orderId": 100,
        "bookingId": 110,
        "serviceId": 1,
        "createdAt": "2022-04-25T10:48:48",
        "status": 2,
        "note": ""
    },
    {
        "orderId": 101,
        "bookingId": 125,
        "serviceId": 3,
        "createdAt": "2022-04-25T10:14:16",
        "status": 2,
        "note": ""
    },
    {
        "orderId": 102,
        "bookingId": 133,
        "serviceId": 3,
        "createdAt": "2022-04-25T12:38:57",
        "status": 2,
        "note": ""
    },
    {
        "orderId": 103,
        "bookingId": 136,
        "serviceId": 4,
        "createdAt": "2022-04-25T12:34:27",
        "status": 2,
        "note": ""
    },
    {
        "orderId": 104,
        "bookingId": 143,
        "serviceId": 1,
        "createdAt": "2022-04-25T10:47:15",
        "status": 2,
        "note": ""
    },
    {
        "orderId": 105,
        "bookingId": 147,
        "serviceId": 3,
        "createdAt": "2022-04-25T12:39:30",
        "status": 2,
        "note": ""
    },
    {
        "orderId": 106,
        "bookingId": 148,
        "serviceId": 1,
        "createdAt": "2022-04-25T10:59:35",
        "status": 2,
        "note": ""
    },
    {
        "orderId": 107,
        "bookingId": 149,
        "serviceId": 2,
        "createdAt": "2022-04-25T12:39:44",
        "status": 2,
        "note": ""
    },
    {
        "orderId": 108,
        "bookingId": 150,
        "serviceId": 2,
        "createdAt": "2022-04-25T11:27:47",
        "status": 2,
        "note": ""
    },
    {
        "orderId": 109,
        "bookingId": 153,
        "serviceId": 3,
        "createdAt": "2022-04-25T10:34:45",
        "status": 2,
        "note": ""
    },
    {
        "orderId": 110,
        "bookingId": 164,
        "serviceId": 3,
        "createdAt": "2022-04-25T11:42:36",
        "status": 2,
        "note": ""
    },
    {
        "orderId": 111,
        "bookingId": 167,
        "serviceId": 1,
        "createdAt": "2022-04-25T12:38:10",
        "status": 2,
        "note": ""
    },
    {
        "orderId": 112,
        "bookingId": 143,
        "serviceId": 1,
        "createdAt": "2022-04-26T10:15:22",
        "status": 2,
        "note": ""
    },
    {
        "orderId": 113,
        "bookingId": 146,
        "serviceId": 3,
        "createdAt": "2022-04-26T10:40:30",
        "status": 2,
        "note": ""
    },
    {
        "orderId": 114,
        "bookingId": 153,
        "serviceId": 2,
        "createdAt": "2022-04-26T12:28:19",
        "status": 2,
        "note": ""
    },
    {
        "orderId": 115,
        "bookingId": 162,
        "serviceId": 4,
        "createdAt": "2022-04-26T12:54:19",
        "status": 2,
        "note": ""
    },
    {
        "orderId": 116,
        "bookingId": 164,
        "serviceId": 2,
        "createdAt": "2022-04-26T10:55:42",
        "status": 2,
        "note": ""
    },
    {
        "orderId": 117,
        "bookingId": 169,
        "serviceId": 5,
        "createdAt": "2022-04-26T12:45:50",
        "status": 2,
        "note": ""
    },
    {
        "orderId": 118,
        "bookingId": 174,
        "serviceId": 5,
        "createdAt": "2022-04-26T11:57:34",
        "status": 2,
        "note": ""
    },
    {
        "orderId": 119,
        "bookingId": 175,
        "serviceId": 3,
        "createdAt": "2022-04-26T10:38:16",
        "status": 2,
        "note": ""
    },
    {
        "orderId": 120,
        "bookingId": 180,
        "serviceId": 1,
        "createdAt": "2022-04-26T11:46:57",
        "status": 2,
        "note": ""
    },
    {
        "orderId": 121,
        "bookingId": 182,
        "serviceId": 1,
        "createdAt": "2022-04-26T11:21:22",
        "status": 2,
        "note": ""
    },
    {
        "orderId": 122,
        "bookingId": 136,
        "serviceId": 4,
        "createdAt": "2022-04-27T11:12:46",
        "status": 2,
        "note": ""
    },
    {
        "orderId": 123,
        "bookingId": 145,
        "serviceId": 3,
        "createdAt": "2022-04-27T11:30:58",
        "status": 2,
        "note": ""
    },
    {
        "orderId": 124,
        "bookingId": 150,
        "serviceId": 4,
        "createdAt": "2022-04-27T10:46:49",
        "status": 2,
        "note": ""
    },
    {
        "orderId": 125,
        "bookingId": 172,
        "serviceId": 4,
        "createdAt": "2022-04-27T10:11:43",
        "status": 2,
        "note": ""
    },
    {
        "orderId": 126,
        "bookingId": 173,
        "serviceId": 5,
        "createdAt": "2022-04-27T10:49:47",
        "status": 2,
        "note": ""
    },
    {
        "orderId": 127,
        "bookingId": 182,
        "serviceId": 1,
        "createdAt": "2022-04-27T10:26:53",
        "status": 2,
        "note": ""
    },
    {
        "orderId": 128,
        "bookingId": 184,
        "serviceId": 4,
        "createdAt": "2022-04-27T11:21:45",
        "status": 2,
        "note": ""
    },
    {
        "orderId": 129,
        "bookingId": 186,
        "serviceId": 5,
        "createdAt": "2022-04-27T12:16:50",
        "status": 2,
        "note": ""
    },
    {
        "orderId": 130,
        "bookingId": 187,
        "serviceId": 2,
        "createdAt": "2022-04-27T11:27:47",
        "status": 2,
        "note": ""
    },
    {
        "orderId": 131,
        "bookingId": 188,
        "serviceId": 4,
        "createdAt": "2022-04-27T10:45:13",
        "status": 2,
        "note": ""
    },
    {
        "orderId": 132,
        "bookingId": 190,
        "serviceId": 5,
        "createdAt": "2022-04-27T10:39:14",
        "status": 2,
        "note": ""
    },
    {
        "orderId": 133,
        "bookingId": 167,
        "serviceId": 5,
        "createdAt": "2022-04-28T11:32:57",
        "status": 2,
        "note": ""
    },
    {
        "orderId": 134,
        "bookingId": 169,
        "serviceId": 4,
        "createdAt": "2022-04-28T10:43:45",
        "status": 2,
        "note": ""
    },
    {
        "orderId": 135,
        "bookingId": 170,
        "serviceId": 4,
        "createdAt": "2022-04-28T12:50:47",
        "status": 2,
        "note": ""
    },
    {
        "orderId": 136,
        "bookingId": 173,
        "serviceId": 4,
        "createdAt": "2022-04-28T12:29:30",
        "status": 2,
        "note": ""
    },
    {
        "orderId": 137,
        "bookingId": 177,
        "serviceId": 5,
        "createdAt": "2022-04-28T12:49:54",
        "status": 2,
        "note": ""
    },
    {
        "orderId": 138,
        "bookingId": 187,
        "serviceId": 2,
        "createdAt": "2022-04-28T10:59:34",
        "status": 2,
        "note": ""
    },
    {
        "orderId": 139,
        "bookingId": 190,
        "serviceId": 5,
        "createdAt": "2022-04-28T11:50:38",
        "status": 2,
        "note": ""
    },
    {
        "orderId": 140,
        "bookingId": 206,
        "serviceId": 4,
        "createdAt": "2022-04-28T11:14:45",
        "status": 2,
        "note": ""
    },
    {
        "orderId": 141,
        "bookingId": 178,
        "serviceId": 2,
        "createdAt": "2022-04-29T12:22:45",
        "status": 2,
        "note": ""
    },
    {
        "orderId": 142,
        "bookingId": 189,
        "serviceId": 3,
        "createdAt": "2022-04-29T10:41:56",
        "status": 2,
        "note": ""
    },
    {
        "orderId": 143,
        "bookingId": 195,
        "serviceId": 5,
        "createdAt": "2022-04-29T12:47:59",
        "status": 2,
        "note": ""
    },
    {
        "orderId": 144,
        "bookingId": 210,
        "serviceId": 1,
        "createdAt": "2022-04-29T11:17:40",
        "status": 2,
        "note": ""
    },
    {
        "orderId": 145,
        "bookingId": 163,
        "serviceId": 5,
        "createdAt": "2022-04-30T12:34:29",
        "status": 2,
        "note": ""
    },
    {
        "orderId": 146,
        "bookingId": 191,
        "serviceId": 3,
        "createdAt": "2022-04-30T12:18:45",
        "status": 2,
        "note": ""
    },
    {
        "orderId": 147,
        "bookingId": 199,
        "serviceId": 4,
        "createdAt": "2022-04-30T10:55:43",
        "status": 2,
        "note": ""
    },
    {
        "orderId": 148,
        "bookingId": 213,
        "serviceId": 1,
        "createdAt": "2022-04-30T11:50:19",
        "status": 2,
        "note": ""
    },
    {
        "orderId": 149,
        "bookingId": 214,
        "serviceId": 1,
        "createdAt": "2022-04-30T10:23:44",
        "status": 2,
        "note": ""
    },
    {
        "orderId": 150,
        "bookingId": 215,
        "serviceId": 1,
        "createdAt": "2022-04-30T10:34:23",
        "status": 2,
        "note": ""
    },
    {
        "orderId": 151,
        "bookingId": 218,
        "serviceId": 2,
        "createdAt": "2022-04-30T10:27:23",
        "status": 2,
        "note": ""
    },
    {
        "orderId": 152,
        "bookingId": 226,
        "serviceId": 1,
        "createdAt": "2022-04-30T11:12:27",
        "status": 2,
        "note": ""
    },
    {
        "orderId": 153,
        "bookingId": 230,
        "serviceId": 1,
        "createdAt": "2022-04-30T12:59:33",
        "status": 2,
        "note": ""
    },
    {
        "orderId": 154,
        "bookingId": 192,
        "serviceId": 2,
        "createdAt": "2022-05-01T10:32:35",
        "status": 2,
        "note": ""
    },
    {
        "orderId": 155,
        "bookingId": 197,
        "serviceId": 3,
        "createdAt": "2022-05-01T10:20:41",
        "status": 2,
        "note": ""
    },
    {
        "orderId": 156,
        "bookingId": 198,
        "serviceId": 4,
        "createdAt": "2022-05-01T12:43:53",
        "status": 2,
        "note": ""
    },
    {
        "orderId": 157,
        "bookingId": 199,
        "serviceId": 3,
        "createdAt": "2022-05-01T12:31:21",
        "status": 2,
        "note": ""
    },
    {
        "orderId": 158,
        "bookingId": 213,
        "serviceId": 4,
        "createdAt": "2022-05-01T10:39:28",
        "status": 2,
        "note": ""
    },
    {
        "orderId": 159,
        "bookingId": 222,
        "serviceId": 3,
        "createdAt": "2022-05-01T12:31:58",
        "status": 2,
        "note": ""
    },
    {
        "orderId": 160,
        "bookingId": 226,
        "serviceId": 2,
        "createdAt": "2022-05-01T12:46:48",
        "status": 2,
        "note": ""
    },
    {
        "orderId": 161,
        "bookingId": 231,
        "serviceId": 3,
        "createdAt": "2022-05-01T11:53:36",
        "status": 2,
        "note": ""
    },
    {
        "orderId": 162,
        "bookingId": 236,
        "serviceId": 3,
        "createdAt": "2022-05-01T11:36:29",
        "status": 2,
        "note": ""
    },
    {
        "orderId": 163,
        "bookingId": 238,
        "serviceId": 1,
        "createdAt": "2022-05-01T11:57:50",
        "status": 2,
        "note": ""
    },
    {
        "orderId": 164,
        "bookingId": 241,
        "serviceId": 5,
        "createdAt": "2022-05-01T12:38:53",
        "status": 2,
        "note": ""
    },
    {
        "orderId": 165,
        "bookingId": 243,
        "serviceId": 1,
        "createdAt": "2022-05-01T12:14:53",
        "status": 2,
        "note": ""
    },
    {
        "orderId": 166,
        "bookingId": 244,
        "serviceId": 4,
        "createdAt": "2022-05-01T12:10:18",
        "status": 2,
        "note": ""
    },
    {
        "orderId": 167,
        "bookingId": 250,
        "serviceId": 4,
        "createdAt": "2022-05-01T11:17:44",
        "status": 2,
        "note": ""
    },
    {
        "orderId": 168,
        "bookingId": 195,
        "serviceId": 3,
        "createdAt": "2022-05-02T12:26:29",
        "status": 2,
        "note": ""
    },
    {
        "orderId": 169,
        "bookingId": 198,
        "serviceId": 4,
        "createdAt": "2022-05-02T11:56:45",
        "status": 2,
        "note": ""
    },
    {
        "orderId": 170,
        "bookingId": 211,
        "serviceId": 2,
        "createdAt": "2022-05-02T10:47:59",
        "status": 2,
        "note": ""
    },
    {
        "orderId": 171,
        "bookingId": 227,
        "serviceId": 4,
        "createdAt": "2022-05-02T11:15:47",
        "status": 2,
        "note": ""
    },
    {
        "orderId": 172,
        "bookingId": 231,
        "serviceId": 3,
        "createdAt": "2022-05-02T11:26:16",
        "status": 2,
        "note": ""
    },
    {
        "orderId": 173,
        "bookingId": 240,
        "serviceId": 1,
        "createdAt": "2022-05-02T11:37:13",
        "status": 2,
        "note": ""
    },
    {
        "orderId": 174,
        "bookingId": 245,
        "serviceId": 1,
        "createdAt": "2022-05-02T11:39:14",
        "status": 2,
        "note": ""
    },
    {
        "orderId": 175,
        "bookingId": 246,
        "serviceId": 4,
        "createdAt": "2022-05-02T10:14:59",
        "status": 2,
        "note": ""
    },
    {
        "orderId": 176,
        "bookingId": 251,
        "serviceId": 3,
        "createdAt": "2022-05-02T10:54:44",
        "status": 2,
        "note": ""
    },
    {
        "orderId": 177,
        "bookingId": 257,
        "serviceId": 3,
        "createdAt": "2022-05-02T12:13:11",
        "status": 2,
        "note": ""
    },
    {
        "orderId": 178,
        "bookingId": 258,
        "serviceId": 4,
        "createdAt": "2022-05-02T10:28:18",
        "status": 2,
        "note": ""
    },
    {
        "orderId": 179,
        "bookingId": 211,
        "serviceId": 1,
        "createdAt": "2022-05-03T12:19:33",
        "status": 2,
        "note": ""
    },
    {
        "orderId": 180,
        "bookingId": 235,
        "serviceId": 1,
        "createdAt": "2022-05-03T10:52:46",
        "status": 2,
        "note": ""
    },
    {
        "orderId": 181,
        "bookingId": 244,
        "serviceId": 1,
        "createdAt": "2022-05-03T11:49:52",
        "status": 2,
        "note": ""
    },
    {
        "orderId": 182,
        "bookingId": 249,
        "serviceId": 4,
        "createdAt": "2022-05-03T10:35:23",
        "status": 2,
        "note": ""
    },
    {
        "orderId": 183,
        "bookingId": 252,
        "serviceId": 5,
        "createdAt": "2022-05-03T12:31:20",
        "status": 2,
        "note": ""
    },
    {
        "orderId": 184,
        "bookingId": 271,
        "serviceId": 5,
        "createdAt": "2022-05-03T11:31:25",
        "status": 2,
        "note": ""
    },
    {
        "orderId": 185,
        "bookingId": 272,
        "serviceId": 5,
        "createdAt": "2022-05-03T11:18:20",
        "status": 2,
        "note": ""
    },
    {
        "orderId": 186,
        "bookingId": 273,
        "serviceId": 1,
        "createdAt": "2022-05-03T12:48:41",
        "status": 2,
        "note": ""
    },
    {
        "orderId": 187,
        "bookingId": 250,
        "serviceId": 5,
        "createdAt": "2022-05-04T10:24:50",
        "status": 2,
        "note": ""
    },
    {
        "orderId": 188,
        "bookingId": 253,
        "serviceId": 4,
        "createdAt": "2022-05-04T10:46:52",
        "status": 1,
        "note": ""
    },
    {
        "orderId": 189,
        "bookingId": 257,
        "serviceId": 5,
        "createdAt": "2022-05-04T10:14:34",
        "status": 1,
        "note": ""
    },
    {
        "orderId": 190,
        "bookingId": 258,
        "serviceId": 3,
        "createdAt": "2022-05-04T10:49:22",
        "status": 1,
        "note": ""
    },
    {
        "orderId": 191,
        "bookingId": 259,
        "serviceId": 2,
        "createdAt": "2022-05-04T10:11:16",
        "status": 2,
        "note": ""
    },
    {
        "orderId": 192,
        "bookingId": 260,
        "serviceId": 1,
        "createdAt": "2022-05-04T10:35:45",
        "status": 1,
        "note": ""
    },
    {
        "orderId": 193,
        "bookingId": 271,
        "serviceId": 2,
        "createdAt": "2022-05-04T10:37:49",
        "status": 2,
        "note": ""
    }
]
